fingerprintswapper/__init__.py
fingerprintswapper-0.0.7.dist-info/METADATA
fingerprintswapper-0.0.7.dist-info/WHEEL
fingerprintswapper-0.0.7.dist-info/top_level.txt
fingerprintswapper-0.0.7.dist-info/RECORD
